stormhub/__init__.py
stormhub/hydro_domain.py
stormhub/logger.py
stormhub/utils.py
stormhub/version.py
stormhub/hydro/__init__.py
stormhub/hydro/plots.py
stormhub/hydro/utils.py
stormhub/hydro/usgs/__init__.py
stormhub/hydro/usgs/usgs.py
stormhub/met/__init__.py
stormhub/met/analysis.py
stormhub/met/consts.py
stormhub/met/storm_catalog.py
stormhub/met/transpose.py
stormhub/met/zarr_to_dss.py
stormhub/met/aorc/__init__.py
stormhub/met/aorc/aorc.py
stormhub/met/dss_utils/add_coords_to_metadata.py
stormhub/met/dss_utils/check_dss.py
stormhub/met/dss_utils/create_dss.py
stormhub/met/dss_utils/create_dss_parallel.py
stormhub/met/dss_utils/create_grid_file.py
stormhub/met/dss_utils/extract_dss_metadata.py
stormhub/met/tests/__init__.py
stormhub/met/tests/transpose_test.py
stormhub/server/__init__.py
stormhub/server/serve.py
stormhub-0.4.0.dist-info/licenses/LICENSE
stormhub-0.4.0.dist-info/METADATA
stormhub-0.4.0.dist-info/WHEEL
stormhub-0.4.0.dist-info/entry_points.txt
stormhub-0.4.0.dist-info/top_level.txt
stormhub-0.4.0.dist-info/RECORD
