Metadata-Version: 2.4
Name: stormhub
Version: 0.4.0
Summary: Create catalogs, data, and metadata for hydrologic modeling in the cloud.
Maintainer-email: Seth Lawler <slawler@dewberry.com>
Project-URL: repository, https://github.com/dewberry/stormhub
Classifier: Development Status :: 4 - Beta
Classifier: Intended Audience :: Developers
Classifier: License :: OSI Approved :: MIT License
Classifier: Programming Language :: Python :: 3
Classifier: Programming Language :: Python :: 3.10
Classifier: Programming Language :: Python :: 3.11
Classifier: Programming Language :: Python :: 3.12
License-File: LICENSE
Requires-Dist: fiona==1.9.6
Requires-Dist: geopandas==1.0.1
Requires-Dist: matplotlib==3.9.0
Requires-Dist: pystac==1.10.0
Requires-Dist: rasterio==1.3.10
Requires-Dist: requests==2.32.3
Requires-Dist: shapely==2.0.5
Requires-Dist: xarray==2024.11.0
Requires-Dist: rioxarray==0.18.1
Requires-Dist: s3fs==2024.12.0
Requires-Dist: zarr==2.18.3
Requires-Dist: dask==2025.1.0
Requires-Dist: numcodecs==0.13.1
Requires-Dist: scipy==1.15.2
Requires-Dist: dataretrieval==1.0.11
Provides-Extra: dev
Requires-Dist: pre-commit; extra == "dev"
Requires-Dist: ruff; extra == "dev"
Requires-Dist: pytest; extra == "dev"
Requires-Dist: pytest-cov; extra == "dev"
Requires-Dist: pytest-json-report; extra == "dev"
Provides-Extra: docs
Requires-Dist: sphinx; extra == "docs"
Requires-Dist: numpydoc; extra == "docs"
Requires-Dist: sphinx_rtd_theme; extra == "docs"
Requires-Dist: sphinx_design; extra == "docs"
Requires-Dist: pydata-sphinx-theme; extra == "docs"
Requires-Dist: sphinx-autodoc-typehints; extra == "docs"
Requires-Dist: myst-parser; extra == "docs"
Dynamic: license-file
